MANIFEST.in
setup.py
dist/django-redactor-0.2.tar.gz
django_redactor.egg-info/PKG-INFO
django_redactor.egg-info/SOURCES.txt
django_redactor.egg-info/dependency_links.txt
django_redactor.egg-info/top_level.txt
redactor/__init__.py
redactor/admin.py
redactor/forms.py
redactor/urls.py
redactor/views.py
redactor/widgets.py
redactor/static/editor/editor.js
redactor/static/editor/css/blank.css
redactor/static/editor/css/editor.css
redactor/static/editor/css/writer.css
redactor/static/editor/i/bg_arctic_silver.png
redactor/static/editor/i/bg_brown.png
redactor/static/editor/i/bg_carrara_white.png
redactor/static/editor/i/bg_cream_white.png
redactor/static/editor/i/bg_guards_red.png
redactor/static/editor/i/bg_macadamia.png
redactor/static/editor/i/bg_racing_green.png
redactor/static/editor/i/close.png
redactor/static/editor/i/hover.png
redactor/static/editor/i/hover_invert.png
redactor/static/editor/i/icons.png
redactor/static/editor/i/icons_invert.png
redactor/static/editor/i/resizer.gif
redactor/static/editor/i/resizer_invert.png
redactor/static/editor/i/separator.png
redactor/static/editor/i/separator_invert.png
redactor/static/editor/i/video_box.png
redactor/static/editor/i/fileicons/avi.png
redactor/static/editor/i/fileicons/csv.png
redactor/static/editor/i/fileicons/doc.png
redactor/static/editor/i/fileicons/gif.png
redactor/static/editor/i/fileicons/html.png
redactor/static/editor/i/fileicons/jpg.png
redactor/static/editor/i/fileicons/mov.png
redactor/static/editor/i/fileicons/other.png
redactor/static/editor/i/fileicons/pdf.png
redactor/static/editor/i/fileicons/png.png
redactor/static/editor/i/fileicons/ppt.png
redactor/static/editor/i/fileicons/rar.png
redactor/static/editor/i/fileicons/rtf.png
redactor/static/editor/i/fileicons/txt.png
redactor/static/editor/i/fileicons/xls.png
redactor/static/editor/i/fileicons/zip.png
redactor/static/editor/langs/en.js
redactor/static/editor/langs/pt_br.js
redactor/static/editor/langs/ru.js
redactor/static/editor/plugins/char.html
redactor/static/editor/plugins/file.html
redactor/static/editor/plugins/file_edit.html
redactor/static/editor/plugins/image.html
