Metadata-Version: 1.0
Name: django-redactor
Version: 0.2
Summary: Django application for http://imperavi.ru/redactor/
Home-page: https://bitbucket.org/gearheart/django-redactor
Author: Vladimir Sidorenko
Author-email: yoyavova@gmail.com
License: UNKNOWN
Platform: UNKNOWN
